Workbook

Sheet LEEME
A1: Base de conocimiento — Coste de la vida (España y Comunidad de Madrid)
A3: Descripción
A4: Precios y gasto: inflación (IPC del INE, IPC armonizado de Eurostat), gasto de los hogares por grupos (EPF), un indicador aproximado de coste de las necesidades básicas, renta y riesgo de pobreza (ECV) y la comparación de salarios con precios (poder adquisitivo).
A5: Fecha de consulta: 2026-10-21. Los cálculos propios están en fórmulas visibles; los marcados en amarillo son aproximaciones no oficiales.
A7: Índice de hojas
A8: Hoja | B8: Contenido | C8: Cobertura
A9: Resumen_Coste_Vida | B9: Indicadores clave de precios, gasto, renta y poder adquisitivo. | C9: Último dato
A10: IPC_General_Anual | B10: Inflación dic/dic de España y Madrid, índice acumulado y media geométrica. | C10: 2002–2025
A11: IPC_2026_Mensual | B11: IPC general, variación anual mensual, España y Madrid. | C11: ene–sep 2026
A12: IPC_Madrid_Grupos | B12: IPC de Madrid por 14 grupos (ECOICOP v2), tasa anual mensual. | C12: ago-2025 a sep-2026
A13: HICP_Espana_Grupos | B13: IPC armonizado de España por grupos, media anual, con acumulado y volatilidad. | C13: 2005–2025
A14: EPF_Madrid_2018_2023 / EPF_Nacional_2018_2023 | B14: Gasto medio por hogar y persona y distribución por grupo. | C14: 2018–2023
A15: EPF_Comparativa_2023 | B15: Madrid frente a España por grupo de gasto, pesos y variación 2018–2023. | C15: 2023
A16: Cesta_Necesidades_Aprox | B16: Indicador aproximado de inflación de las necesidades básicas en Madrid (5 grupos ponderados). | C16: sep-2025 y sep-2026
A17: Salario_vs_IPC | B17: Salario medio/mediano nominal y real frente al IPC acumulado. | C17: 2008–2024
A18: ECV_Renta_Pobreza | B18: Renta neta media y AROPE, Madrid y España. | C18: 2020–2025
A19: FUENTES | B19: Origen de cada bloque.
A21: Notas, límites y huecos conocidos
A22: • No existe una "cesta de la compra básica" oficial única en España. La hoja Cesta_Necesidades_Aprox es un proxy propio con cinco grupos esenciales (alimentos, vivienda y suministros, sanidad, transporte, enseñanza) ponderados con el gasto de los hogares de Madrid; no sustituye a una cesta oficial.
A23: • El IPC del INE cambió a base 2025 y ECOICOP v2 en 2026 (14 grupos). Los grupos de la EPF (12, ECOICOP v1) y del HICP de Eurostat (nomenclatura anterior) no coinciden exactamente con los de 2026.
A24: • IPC de Madrid por grupo: solo 14 meses (ago-2025 a sep-2026). No se descargó el histórico por grupo ni por subclase de Madrid, ni los precios medios de productos concretos (pan, leche, huevos, etc.).
A25: • HICP: falta el grupo CP08 (Comunicaciones) por límite de peticiones de Eurostat; las cifras son del IPC armonizado, que no coincide con el IPC nacional.
A26: • EPF: último año publicado 2023 (el INE publica con retraso). Los importes son nominales. La EPF por CCAA completa (todas las comunidades) y por quintiles de renta no se descargó.
A27: • ECV: los años son los de la encuesta; la renta se refiere al año anterior. Falta carencia material por CCAA, tenencia de vivienda y sobrecarga de coste de vivienda.
A28: • Pendiente: IPC por provincia y por subclases, precios de energía (electricidad, gas, carburantes) y niveles de precios comparados de Eurostat.
A30: Convención de colores
A31: Azul: dato copiado de la fuente (valor fijo)
A32: Negro: fórmula de esta hoja
A33: Verde: fórmula que enlaza con otra hoja
... A35: Fondo amarillo claro: estimación no oficial (elaboración propia)

Sheet Resumen_Coste_Vida
A1: Resumen del coste de la vida — España y Comunidad de Madrid
A2: Los valores enlazan con las hojas de detalle (verde). IPC base 2025 del INE hasta septiembre de 2026; EPF y ECV en su último año publicado.
A4: Indicador | B4: Periodo | C4: España | D4: Madrid | E4: Madrid − España | F4: Nota
A5: IPC general, variación anual (%) | B5: sep-2026 | C5: =IPC_2026_Mensual!B10 -> 4.9 | D5: =IPC_2026_Mensual!C10 -> 5.3 | E5: =D5-C5 -> 0.4 | F5: IPC_2026_Mensual
A6: IPC general, dic/dic (%) | B6: 2025 | C6: =IPC_General_Anual!B25 -> 2.9 | D6: =IPC_General_Anual!C25 -> 3.7 | E6: =D6-C6 -> 0.8 | F6: IPC_General_Anual
A7: Inflación acumulada 2002–2025 (%) | B7: 2002–2025 | C7: =IPC_General_Anual!E27 -> 72.292045 | D7: =IPC_General_Anual!F27 -> 70.161692 | E7: =D7-C7 -> -2.1303526 | F7: Encadenado dic/dic (cálculo propio)
A8: Grupo con mayor inflación en Madrid | B8: sep-2026 | C8: =INDEX(IPC_Madrid_Grupos!A3:A15,MATCH(MAX(IPC_Madrid_Grupos!O3:O15),IPC_Madrid_Grupos!O3:O15,0)) -> Transporte | D8: =MAX(IPC_Madrid_Grupos!O3:O15) -> 11.5 | F8: Col. España = nombre del grupo; col. Madrid = tasa anual (%)
A9: Necesidades básicas (aprox., ponderado EPF), variación anual (%) | B9: sep-2026 | D9: =Cesta_Necesidades_Aprox!D10 -> 5.9576777 | F9: Cálculo propio, solo Madrid
A10: IPC armonizado España, media anual (%) | B10: 2025 | C10: =HICP_Espana_Grupos!W2 -> 2.7 | F10: Eurostat, solo España
A11: Gasto medio por hogar (€) | B11: 2023 | C11: =EPF_Comparativa_2023!C2 -> 32616.66 | D11: =EPF_Comparativa_2023!B2 -> 37360.47 | E11: =D11-C11 -> 4743.81 | F11: EPF_Comparativa_2023
A12: Gasto medio por persona (€) | B12: 2023 | C12: =EPF_Comparativa_2023!F2 -> 13120.1 | D12: =EPF_Comparativa_2023!E2 -> 14650.11 | E12: =D12-C12 -> 1530.01 | F12: EPF_Comparativa_2023
A13: % del gasto en vivienda y suministros | B13: 2023 | C13: =EPF_Comparativa_2023!H6 -> 31.79 | D13: =EPF_Comparativa_2023!G6 -> 35 | E13: =D13-C13 -> 3.21 | F13: EPF_Comparativa_2023
A14: % del gasto en alimentos y bebidas no alcohólicas | B14: 2023 | C14: =EPF_Comparativa_2023!H3 -> 16.35 | D14: =EPF_Comparativa_2023!G3 -> 14.01 | E14: =D14-C14 -> -2.34 | F14: EPF_Comparativa_2023
A15: Renta neta media por persona (€) | B15: 2025 | C15: =ECV_Renta_Pobreza!E2 -> 15620 | D15: =ECV_Renta_Pobreza!E6 -> 18169 | E15: =D15-C15 -> 2549 | F15: ECV (renta del año anterior a la encuesta)
A16: AROPE (riesgo de pobreza o exclusión, %) | B16: 2025 | C16: =ECV_Renta_Pobreza!I23 -> 25.7 | D16: =ECV_Renta_Pobreza!I19 -> 19.4 | E16: =D16-C16 -> -6.3 | F16: ECV_Renta_Pobreza
A17: Salario medio real 2024 (2008=100) | B17: 2024 | C17: =Salario_vs_IPC!N18 -> 99.899781 | D17: =Salario_vs_IPC!P18 -> 102.63631 | E17: =D17-C17 -> 2.7365311 | F17: Salario_vs_IPC (deflactado con IPC dic/dic)
A18: Salario mediano real 2024 (2008=100) | B18: 2024 | C18: =Salario_vs_IPC!O18 -> 99.36919 | D18: =Salario_vs_IPC!Q18 -> 104.25886 | E18: =D18-C18 -> 4.8896707 | F18: Salario_vs_IPC

Sheet IPC_General_Anual
A1: anio | B1: España_dic/dic_% | C1: Madrid_dic/dic_% | D1: Madrid − España (pp) | E1: Índice acumulado España (dic 2001=100) | F1: Índice acumulado Madrid (dic 2001=100)
A2: 2002 | B2: 4 | C2: 3.9 | D2: =C2-B2 -> -0.1 | E2: =100*(1+B2/100) -> 104 | F2: =100*(1+C2/100) -> 103.9
A3: 2003 | B3: 2.6 | C3: 2.6 | D3: =C3-B3 -> 0 | E3: =E2*(1+B3/100) -> 106.704 | F3: =F2*(1+C3/100) -> 106.6014
A4: 2004 | B4: 3.2 | C4: 3.1 | D4: =C4-B4 -> -0.1 | E4: =E3*(1+B4/100) -> 110.11853 | F4: =F3*(1+C4/100) -> 109.90604
A5: 2005 | B5: 3.7 | C5: 3.7 | D5: =C5-B5 -> 0 | E5: =E4*(1+B5/100) -> 114.19291 | F5: =F4*(1+C5/100) -> 113.97257
A6: 2006 | B6: 2.7 | C6: 2.7 | D6: =C6-B6 -> 0 | E6: =E5*(1+B6/100) -> 117.27612 | F6: =F5*(1+C6/100) -> 117.04983
A7: 2007 | B7: 4.2 | C7: 4 | D7: =C7-B7 -> -0.2 | E7: =E6*(1+B7/100) -> 122.20172 | F7: =F6*(1+C7/100) -> 121.73182
A8: 2008 | B8: 1.4 | C8: 1.6 | D8: =C8-B8 -> 0.2 | E8: =E7*(1+B8/100) -> 123.91254 | F8: =F7*(1+C8/100) -> 123.67953
A9: 2009 | B9: 0.8 | C9: 0.9 | D9: =C9-B9 -> 0.1 | E9: =E8*(1+B9/100) -> 124.90384 | F9: =F8*(1+C9/100) -> 124.79264
A10: 2010 | B10: 3 | C10: 3 | D10: =C10-B10 -> 0 | E10: =E9*(1+B10/100) -> 128.65096 | F10: =F9*(1+C10/100) -> 128.53642
A11: 2011 | B11: 2.4 | C11: 2.5 | D11: =C11-B11 -> 0.1 | E11: =E10*(1+B11/100) -> 131.73858 | F11: =F10*(1+C11/100) -> 131.74983
A12: 2012 | B12: 2.9 | C12: 2.5 | D12: =C12-B12 -> -0.4 | E12: =E11*(1+B12/100) -> 135.559 | F12: =F11*(1+C12/100) -> 135.04358
A13: 2013 | B13: 0.3 | C13: 0.2 | D13: =C13-B13 -> -0.1 | E13: =E12*(1+B13/100) -> 135.96568 | F13: =F12*(1+C13/100) -> 135.31367
A14: 2014 | B14: -1 | C14: -1.1 | D14: =C14-B14 -> -0.1 | E14: =E13*(1+B14/100) -> 134.60602 | F14: =F13*(1+C14/100) -> 133.82522
... A25: 2025 | B25: 2.9 | C25: 3.7 | D25: =C25-B25 -> 0.8 | E25: =E24*(1+B25/100) -> 172.29204 | F25: =F24*(1+C25/100) -> 170.16169
A27: Inflación acumulada 2002–2025 (%) | E27: =(E25/100-1)*100 -> 72.292045 | F27: =(F25/100-1)*100 -> 70.161692
A28: Media anual geométrica (%) | E28: =((E25/100)^(1/24)-1)*100 -> 2.2926394 | F28: =((F25/100)^(1/24)-1)*100 -> 2.2396235
A30: IPC base 2025 (ECOICOP v2) del INE, tasa de variación anual de diciembre sobre diciembre del índice general (series IPC290750 España e IPC294331 Madrid). El índice acumulado es cálculo propio encadenando las tasas.

Sheet IPC_2026_Mensual
A1: mes | B1: España_tasa_anual_% | C1: Madrid_tasa_anual_% | D1: Madrid − España (pp)
A2: 2026-01 | B2: 2.3 | C2: 3 | D2: =C2-B2 -> 0.7
A3: 2026-02 | B3: 2.3 | C3: 2.9 | D3: =C3-B3 -> 0.6
A4: 2026-03 | B4: 3.4 | C4: 4.1 | D4: =C4-B4 -> 0.7
A5: 2026-04 | B5: 3.2 | C5: 3.8 | D5: =C5-B5 -> 0.6
A6: 2026-05 | B6: 3.2 | C6: 3.8 | D6: =C6-B6 -> 0.6
A7: 2026-06 | B7: 3.2 | C7: 3.8 | D7: =C7-B7 -> 0.6
A8: 2026-07 | B8: 3.6 | C8: 3.9 | D8: =C8-B8 -> 0.3
A9: 2026-08 | B9: 4.3 | C9: 4.7 | D9: =C9-B9 -> 0.4
A10: 2026-09 | B10: 4.9 | C10: 5.3 | D10: =C10-B10 -> 0.4
A12: Tasa de variación anual del IPC general (INE, series IPC290750 y IPC294331).

Sheet IPC_Madrid_Grupos
A1: grupo ECOICOP v2 | B1: 2025-08 | C1: 2025-09 | D1: 2025-10 | E1: 2025-11 | F1: 2025-12 | G1: 2026-01 | H1: 2026-02 | I1: 2026-03 | J1: 2026-04 | K1: 2026-05 | L1: 2026-06 | M1: 2026-07 | N1: 2026-08 | O1: 2026-09 | P1: media_14_meses | Q1: último_mes − general (pp)
A2: Índice general | B2: 2.9 | C2: 3.5 | D2: 3.6 | E2: 3.7 | F2: 3.7 | G2: 3 | H2: 2.9 | I2: 4.1 | J2: 3.8 | K2: 3.8 | L2: 3.8 | M2: 3.9 | N2: 4.7 | O2: 5.3 | P2: =AVERAGE(B2:O2) -> 3.7642857 | Q2: =O2-O$2 -> 0
A3: Alimentos y bebidas no alcohólicas | B3: 2.6 | C3: 2.7 | D3: 2.8 | E3: 3.2 | F3: 3.4 | G3: 3.4 | H3: 3.7 | I3: 3.2 | J3: 3.3 | K3: 2.8 | L3: 2.5 | M3: 2.2 | N3: 3.1 | O3: 3.2 | P3: =AVERAGE(B3:O3) -> 3.0071429 | Q3: =O3-O$2 -> -2.1
A4: Bebidas alcohólicas y tabaco | B4: 4.1 | C4: 4.2 | D4: 4.6 | E4: 5 | F4: 5 | G4: 4.5 | H4: 5.2 | I4: 4.5 | J4: 4.8 | K4: 4 | L4: 3 | M4: 2.7 | N4: 3.3 | O4: 2.8 | P4: =AVERAGE(B4:O4) -> 4.1214286 | Q4: =O4-O$2 -> -2.5
A5: Vestido y calzado | B5: 0.5 | C5: 0.3 | D5: 0.6 | E5: 1.3 | F5: 1.3 | G5: -0.5 | H5: -0.6 | I5: 1.5 | J5: 1.4 | K5: -1 | L5: -0.9 | M5: -1.8 | N5: -2 | O5: 0.5 | P5: =AVERAGE(B5:O5) -> 0.042857143 | Q5: =O5-O$2 -> -4.8
A6: Vivienda, agua, electricidad, gas y otros combustibles | B6: 4.9 | C6: 7.8 | D6: 8.2 | E6: 6.8 | F6: 6.9 | G6: 4.8 | H6: 4.1 | I6: 5 | J6: 3.4 | K6: 3.1 | L6: 6.2 | M6: 7.1 | N6: 7.6 | O6: 5.9 | P6: =AVERAGE(B6:O6) -> 5.8428571 | Q6: =O6-O$2 -> 0.6
A7: Muebles y artículos del hogar | B7: 1 | C7: 0.9 | D7: 1.1 | E7: 1.1 | F7: 1 | G7: 0.3 | H7: 0.6 | I7: 0.7 | J7: 1 | K7: 1 | L7: 1.1 | M7: 1.1 | N7: 1.1 | O7: 1.1 | P7: =AVERAGE(B7:O7) -> 0.93571429 | Q7: =O7-O$2 -> -4.2
A8: Sanidad | B8: 2.2 | C8: 2.3 | D8: 2.6 | E8: 3.1 | F8: 3.2 | G8: 2.9 | H8: 3.1 | I8: 2.7 | J8: 2.5 | K8: 2.5 | L8: 2.5 | M8: 2.4 | N8: 2.6 | O8: 2.6 | P8: =AVERAGE(B8:O8) -> 2.6571429 | Q8: =O8-O$2 -> -2.7
A9: Transporte | B9: 2.8 | C9: 3.7 | D9: 4.2 | E9: 4.1 | F9: 3.7 | G9: 1.7 | H9: 1.4 | I9: 7.3 | J9: 7.8 | K9: 9.1 | L9: 6.5 | M9: 5.9 | N9: 9.6 | O9: 11.5 | P9: =AVERAGE(B9:O9) -> 5.6642857 | Q9: =O9-O$2 -> 6.2
A10: Información y comunicaciones | B10: 0.1 | C10: 0 | D10: 0.9 | E10: 1.1 | F10: 0.9 | G10: -0.3 | H10: -0.3 | I10: 0.2 | J10: 0.3 | K10: -0.2 | L10: -0.2 | M10: 1.7 | N10: 2.7 | O10: 2.8 | P10: =AVERAGE(B10:O10) -> 0.69285714 | Q10: =O10-O$2 -> -2.5
A11: Actividades recreativas deporte y cultura | B11: 1.2 | C11: 0.5 | D11: 0.2 | E11: 1.1 | F11: 0.7 | G11: 2.2 | H11: 1.6 | I11: 2.4 | J11: 0.9 | K11: 2.5 | L11: 1.9 | M11: 2 | N11: 0.8 | O11: 4 | P11: =AVERAGE(B11:O11) -> 1.5714286 | Q11: =O11-O$2 -> -1.3
A12: Enseñanza | B12: 2.6 | C12: 2.8 | D12: 2.7 | E12: 2.8 | F12: 2.8 | G12: 2.8 | H12: 2.8 | I12: 2.8 | J12: 2.8 | K12: 2.7 | L12: 2.7 | M12: 2.7 | N12: 2.6 | O12: 2.1 | P12: =AVERAGE(B12:O12) -> 2.6928571 | Q12: =O12-O$2 -> -3.2
A13: Restaurantes y servicios de alojamiento | B13: 3.8 | C13: 4.6 | D13: 4.1 | E13: 4.4 | F13: 5 | G13: 4.7 | H13: 4.3 | I13: 4.4 | J13: 4.3 | K13: 4 | L13: 5.2 | M13: 4.7 | N13: 4.8 | O13: 5.7 | P13: =AVERAGE(B13:O13) -> 4.5714286 | Q13: =O13-O$2 -> 0.4
... A15: Cuidado personal protección social y servicios diversos | B15: 4.2 | C15: 4.1 | D15: 4 | E15: 4.2 | F15: 4.1 | G15: 3.4 | H15: 3.7 | I15: 3.7 | J15: 3.8 | K15: 3.3 | L15: 3.2 | M15: 2.9 | N15: 2.9 | O15: 2.8 | P15: =AVERAGE(B15:O15) -> 3.5928571 | Q15: =O15-O$2 -> -2.5
A17: Comunidad de Madrid, tasa de variación anual (%) por grupo (INE, IPC base 2025, tabla 76136). Agosto 2025 – septiembre 2026.

Sheet HICP_Espana_Grupos
A1: coicop | B1: grupo | C1: 2005 | D1: 2006 | E1: 2007 | F1: 2008 | G1: 2009 | H1: 2010 | I1: 2011 | J1: 2012 | K1: 2013 | L1: 2014 | M1: 2015 | N1: 2016 | O1: 2017 | P1: 2018 | Q1: 2019 | R1: 2020 | S1: 2021 | T1: 2022 | U1: 2023 | V1: 2024 | W1: 2025 | X1: media_aritmética_% | Y1: acumulado_2005-2025_% | Z1: volatilidad (DT)
A2: CP00 | B2: Índice general | C2: 3.4 | D2: 3.6 | E2: 2.8 | F2: 4.1 | G2: -0.2 | H2: 2 | I2: 3 | J2: 2.4 | K2: 1.5 | L2: -0.2 | M2: -0.6 | N2: -0.3 | O2: 2 | P2: 1.7 | Q2: 0.8 | R2: -0.3 | S2: 3 | T2: 8.3 | U2: 3.4 | V2: 2.9 | W2: 2.7 | X2: =AVERAGE(C2:W2) -> 2.1904762 | Y2: =(EXP(SUMPRODUCT(LN(1+C2:W2/100)))-1)*100 -> 57.006999 | Z2: =STDEV(C2:W2) -> 2.0336924
A3: CP01 | B3: Alimentos y bebidas no alcohólicas | C3: 3.2 | D3: 4.2 | E3: 3.7 | F3: 5.9 | G3: -1.1 | H3: -0.4 | I3: 1.7 | J3: 2.1 | K3: 2.8 | L3: -0.4 | M3: 1.2 | N3: 1.4 | O3: 1.2 | P3: 1.6 | Q3: 1 | R3: 2.4 | S3: 1.8 | T3: 11.6 | U3: 11.7 | V3: 3.6 | W3: 2.5 | X3: =AVERAGE(C3:W3) -> 2.9380952 | Y3: =(EXP(SUMPRODUCT(LN(1+C3:W3/100)))-1)*100 -> 81.861051 | Z3: =STDEV(C3:W3) -> 3.3153395
A4: CP04 | B4: Vivienda agua electricidad gas y otros combustibles | C4: 5.3 | D4: 6.5 | E4: 3.7 | F4: 6.6 | G4: 1.3 | H4: 3.8 | I4: 7.2 | J4: 5 | K4: 0.9 | L4: 1.3 | M4: -2.3 | N4: -4.2 | O4: 3.9 | P4: 2.3 | Q4: -1.4 | R4: -3.5 | S4: 11 | T4: 15.3 | U4: -11 | V4: 3.6 | W4: 6.1 | X4: =AVERAGE(C4:W4) -> 2.9238095 | Y4: =(EXP(SUMPRODUCT(LN(1+C4:W4/100)))-1)*100 -> 77.737206 | Z4: =STDEV(C4:W4) -> 5.6010628
A5: CP07 | B5: Transporte | C5: 6.4 | D5: 4.6 | E5: 2.1 | F5: 6.1 | G5: -5.6 | H5: 7.4 | I5: 8 | J5: 5.1 | K5: 1.2 | L5: -1 | M5: -5.2 | N5: -2.8 | O5: 4 | P5: 3.5 | Q5: 1.1 | R5: -3.7 | S5: 7.1 | T5: 11.7 | U5: -0.6 | V5: 0.7 | W5: 0.7 | X5: =AVERAGE(C5:W5) -> 2.4190476 | Y5: =(EXP(SUMPRODUCT(LN(1+C5:W5/100)))-1)*100 -> 61.862631 | Z5: =STDEV(C5:W5) -> 4.6156927
A6: CP11 | B6: Restaurantes y hoteles | C6: 4.2 | D6: 4.5 | E6: 4.8 | F6: 4.7 | G6: 1.9 | H6: 1 | I6: 1.6 | J6: 0.9 | K6: 0.5 | L6: 0.5 | M6: 1 | N6: 1.1 | O6: 2.3 | P6: 2 | Q6: 2.1 | R6: 0.8 | S6: 0.7 | T6: 7.4 | U6: 6.6 | V6: 4.9 | W6: 4.4 | X6: =AVERAGE(C6:W6) -> 2.7571429 | Y6: =(EXP(SUMPRODUCT(LN(1+C6:W6/100)))-1)*100 -> 76.281234 | Z6: =STDEV(C6:W6) -> 2.128279
A7: CP02 | B7: Bebidas alcohólicas y tabaco | C7: 5.1 | D7: 1.9 | E7: 7 | F7: 4 | G7: 8.9 | H7: 10.9 | I7: 10.2 | J7: 5.9 | K7: 6.1 | L7: 1.4 | M7: 1.4 | N7: 0.5 | O7: 1.7 | P7: 1.9 | Q7: 0.7 | R7: 0.5 | S7: 0.3 | T7: 3.9 | U7: 7.6 | V7: 4 | W7: 3.9 | X7: =AVERAGE(C7:W7) -> 4.1809524 | Y7: =(EXP(SUMPRODUCT(LN(1+C7:W7/100)))-1)*100 -> 134.02199 | Z7: =STDEV(C7:W7) -> 3.2961522
A8: CP03 | B8: Vestido y calzado | C8: 1.4 | D8: 1.2 | E8: 1.1 | F8: 0.7 | G8: -1.7 | H8: 1.8 | I8: 0.5 | J8: 0.7 | K8: 0.4 | L8: 0.4 | M8: 0.5 | N8: 0.8 | O8: 0.8 | P8: 1.3 | Q8: 1.1 | R8: 0.7 | S8: 1 | T8: 0 | U8: 0.2 | V8: 1.7 | W8: -0.8 | X8: =AVERAGE(C8:W8) -> 0.65714286 | Y8: =(EXP(SUMPRODUCT(LN(1+C8:W8/100)))-1)*100 -> 14.673288 | Z8: =STDEV(C8:W8) -> 0.79722734
A9: CP05 | B9: Mobiliario y equipamiento del hogar | C9: 2.1 | D9: 2.6 | E9: 2.6 | F9: 2.6 | G9: 1.5 | H9: 0.6 | I9: 1.1 | J9: 0.9 | K9: 0.9 | L9: -0.5 | M9: -0.2 | N9: 0.2 | O9: -0.4 | P9: 0.1 | Q9: 0.6 | R9: 0.4 | S9: 1 | T9: 6.4 | U9: 5 | V9: 0.7 | W9: 0.7 | X9: =AVERAGE(C9:W9) -> 1.3761905 | Y9: =(EXP(SUMPRODUCT(LN(1+C9:W9/100)))-1)*100 -> 32.868805 | Z9: =STDEV(C9:W9) -> 1.7221802
A10: CP06 | B10: Sanidad | C10: 0.9 | D10: 1.3 | E10: -1.5 | F10: 0.2 | G10: -0.7 | H10: -1 | I10: -1.3 | J10: 3.5 | K10: 6.9 | L10: 0.1 | M10: 0.1 | N10: 0.4 | O10: 0.7 | P10: 0.3 | Q10: 0.8 | R10: 0.4 | S10: 0.7 | T10: 1.1 | U10: 1.9 | V10: 2 | W10: 2 | X10: =AVERAGE(C10:W10) -> 0.8952381 | Y10: =(EXP(SUMPRODUCT(LN(1+C10:W10/100)))-1)*100 -> 20.200392 | Z10: =STDEV(C10:W10) -> 1.8147937
A11: CP09 | B11: Ocio y cultura | C11: -0.2 | D11: 0.2 | E11: -0.7 | F11: -0.1 | G11: -0.4 | H11: -1.2 | I11: -0.1 | J11: 0.7 | K11: 0.7 | L11: -1.4 | M11: -0.4 | N11: -1 | O11: 0.9 | P11: -0.2 | Q11: -0.6 | R11: -0.8 | S11: 0.2 | T11: 3.7 | U11: 5.8 | V11: 3.1 | W11: 1.2 | X11: =AVERAGE(C11:W11) -> 0.44761905 | Y11: =(EXP(SUMPRODUCT(LN(1+C11:W11/100)))-1)*100 -> 9.5005366 | Z11: =STDEV(C11:W11) -> 1.7656781
A12: CP10 | B12: Educación | C12: 4.2 | D12: 4 | E12: 4.5 | F12: 4 | G12: 3.5 | H12: 2.5 | I12: 2.4 | J12: 4.8 | K12: 8.1 | L12: 1.8 | M12: 1.1 | N12: 0.6 | O12: 0.9 | P12: 0.8 | Q12: 1 | R12: 0.6 | S12: 0.2 | T12: 1.3 | U12: 2 | V12: 2.7 | W12: 2.5 | X12: =AVERAGE(C12:W12) -> 2.547619 | Y12: =(EXP(SUMPRODUCT(LN(1+C12:W12/100)))-1)*100 -> 69.021305 | Z12: =STDEV(C12:W12) -> 1.915625
A13: CP12 | B13: Bienes y servicios diversos | C13: 2.8 | D13: 3.9 | E13: 3.4 | F13: 3.4 | G13: 2.2 | H13: 1.9 | I13: 2.6 | J13: 2.4 | K13: 2.2 | L13: 0.3 | M13: 1 | N13: 0.9 | O13: 1 | P13: 1.1 | Q13: 1.6 | R13: 1.6 | S13: 1.1 | T13: 3.6 | U13: 4.5 | V13: 3.3 | W13: 3.6 | X13: =AVERAGE(C13:W13) -> 2.3047619 | Y13: =(EXP(SUMPRODUCT(LN(1+C13:W13/100)))-1)*100 -> 61.151269 | Z13: =STDEV(C13:W13) -> 1.1817259
A15: IPC armonizado (HICP) de España, tasa de variación media anual (%), Eurostat prc_hicp_aind. No incluye el grupo CP08 (Comunicaciones): Eurostat limitó las peticiones (HTTP 429) al consultarlo y no se reintentó. Eurostat marca este dataset como discontinuado y sustituido por prc_hicp_ainr (nomenclatura ECOICOP v2).

Sheet EPF_Madrid_2018_2023
A1: serie | B1: 2018 | C1: 2019 | D1: 2020 | E1: 2021 | F1: 2022 | G1: 2023
A2: Índice general - Gasto medio por hogar | B2: 34793.11 | C2: 35798.09 | D2: 32502.41 | E2: 34326.24 | F2: 36197.93 | G2: 37360.47
A3: Índice general - Gasto medio por persona | B3: 14021.4 | C3: 14283.93 | D3: 12873.35 | E3: 13541.01 | F3: 14325.91 | G3: 14650.11
A4: Alimentos y bebidas no alcohólicas - Gasto medio por hogar | B4: 4129.36 | C4: 4261.88 | D4: 4670.16 | E4: 4696.73 | F4: 5115.86 | G4: 5235.2
A5: Alimentos y bebidas no alcohólicas - Gasto medio por persona | B5: 1664.11 | C5: 1700.55 | D5: 1849.73 | E5: 1852.77 | F5: 2024.68 | G5: 2052.87
A6: Alimentos y bebidas no alcohólicas - Distribución % | B6: 11.87 | C6: 11.91 | D6: 14.37 | E6: 13.68 | F6: 14.13 | G6: 14.01
A7: Bebidas alcohólicas y tabaco - Gasto medio por hogar | B7: 493.47 | C7: 541.79 | D7: 525.27 | E7: 471.36 | F7: 458.34 | G7: 457.73
A8: Bebidas alcohólicas y tabaco - Gasto medio por persona | B8: 198.86 | C8: 216.18 | D8: 208.04 | E8: 185.94 | F8: 181.4 | G8: 179.49
A9: Bebidas alcohólicas y tabaco - Distribución % | B9: 1.42 | C9: 1.51 | D9: 1.62 | E9: 1.37 | F9: 1.27 | G9: 1.23
A10: Vestido y calzado - Gasto medio por hogar | B10: 1487.95 | C10: 1567.38 | D10: 1141.16 | E10: 1238.43 | F10: 1235.35 | G10: 1323.8
A11: Vestido y calzado - Gasto medio por persona | B11: 599.63 | C11: 625.4 | D11: 451.98 | E11: 488.54 | F11: 488.91 | G11: 519.1
A12: Vestido y calzado - Distribución % | B12: 4.28 | C12: 4.38 | D12: 3.51 | E12: 3.61 | F12: 3.41 | G12: 3.54
A13: Vivienda agua electricidad gas y otros combustibles - Gasto medio por hogar | B13: 11729.82 | C13: 12053.14 | D13: 12877.71 | E13: 12627 | F13: 12889.66 | G13: 13076.74
... A39: Otros bienes y servicios - Distribución % | B39: 7.34 | C39: 7.33 | D39: 7.59 | E39: 7.7 | F39: 7.3 | G39: 7.08
A41: Encuesta de Presupuestos Familiares (INE, base 2006, tabla 14505). Euros por hogar / por persona y distribución porcentual del gasto por grupo ECOICOP (v1, 12 grupos).

Sheet EPF_Nacional_2018_2023
A1: serie | B1: 2018 | C1: 2019 | D1: 2020 | E1: 2021 | F1: 2022 | G1: 2023
A2: General - Gasto medio por hogar | B2: 29871.28 | C2: 30242.76 | D2: 26995.76 | E2: 29243.61 | F2: 31567.71 | G2: 32616.66
A3: General - Gasto medio por persona | B3: 12018.94 | C3: 12151.5 | D3: 10848.22 | E3: 11779.97 | F3: 12779.54 | G3: 13120.1
A4: Alimentos y bebidas no alcohólicas - Gasto medio por hogar | B4: 4223.33 | C4: 4286 | D4: 4578.87 | E4: 4805.82 | F4: 5050.24 | G4: 5333.49
A5: Alimentos y bebidas no alcohólicas - Gasto medio por persona | B5: 1699.29 | C5: 1722.11 | D5: 1840.02 | E5: 1935.89 | F5: 2044.49 | G5: 2145.4
A6: Alimentos y bebidas no alcohólicas - Distribución % | B6: 14.14 | C6: 14.17 | D6: 16.96 | E6: 16.43 | F6: 16 | G6: 16.35
A7: Bebidas alcohólicas y tabaco - Gasto medio por hogar | B7: 518.88 | C7: 516.29 | D7: 510.21 | E7: 495.63 | F7: 480.75 | G7: 473.61
A8: Bebidas alcohólicas y tabaco - Gasto medio por persona | B8: 208.77 | C8: 207.44 | D8: 205.03 | E8: 199.65 | F8: 194.62 | G8: 190.51
A9: Bebidas alcohólicas y tabaco - Distribución % | B9: 1.74 | C9: 1.71 | D9: 1.89 | E9: 1.69 | F9: 1.52 | G9: 1.45
A10: Vestido y calzado - Gasto medio por hogar | B10: 1463.11 | C10: 1417.49 | D10: 1009.03 | E10: 1155.97 | F10: 1231.61 | G10: 1319.38
A11: Vestido y calzado - Gasto medio por persona | B11: 588.69 | C11: 569.55 | D11: 405.48 | E11: 465.65 | F11: 498.59 | G11: 530.72
A12: Vestido y calzado - Distribución % | B12: 4.9 | C12: 4.69 | D12: 3.74 | E12: 3.95 | F12: 3.9 | G12: 4.05
A13: Vivienda agua electricidad gas y otros combustibles - Gasto medio por hogar | B13: 9180.75 | C13: 9441.17 | D13: 9621.46 | E13: 9893.03 | F13: 10242.59 | G13: 10367.26
... A39: Otros bienes y servicios - Distribución % | B39: 7.69 | C39: 7.57 | D39: 7.81 | E39: 7.58 | F39: 7.49 | G39: 7.39
A41: Encuesta de Presupuestos Familiares (INE, base 2006, tabla 14505). Euros por hogar / por persona y distribución porcentual del gasto por grupo ECOICOP (v1, 12 grupos).

Sheet EPF_Comparativa_2023
A1: grupo de gasto | B1: gasto_hogar_Madrid_€ | C1: gasto_hogar_España_€ | D1: ratio Madrid/España | E1: gasto_persona_Madrid_€ | F1: gasto_persona_España_€ | G1: peso_Madrid_% | H1: peso_España_% | I1: dif_peso_pp | J1: var_2018-2023_Madrid_% | K1: var_2018-2023_España_%
A2: TOTAL | B2: =EPF_Madrid_2018_2023!G2 -> 37360.47 | C2: =EPF_Nacional_2018_2023!G2 -> 32616.66 | D2: =B2/C2 -> 1.1454413 | E2: =EPF_Madrid_2018_2023!G3 -> 14650.11 | F2: =EPF_Nacional_2018_2023!G3 -> 13120.1 | G2: =SUM(G3:G14) -> 99.99 | H2: =SUM(H3:H14) -> 100.01 | J2: =(EPF_Madrid_2018_2023!G2/EPF_Madrid_2018_2023!B2-1)*100 -> 7.3789322 | K2: =(EPF_Nacional_2018_2023!G2/EPF_Nacional_2018_2023!B2-1)*100 -> 9.1907009
A3: Alimentos y bebidas no alcohólicas | B3: =EPF_Madrid_2018_2023!G4 -> 5235.2 | C3: =EPF_Nacional_2018_2023!G4 -> 5333.49 | D3: =B3/C3 -> 0.98157117 | E3: =EPF_Madrid_2018_2023!G5 -> 2052.87 | F3: =EPF_Nacional_2018_2023!G5 -> 2145.4 | G3: =EPF_Madrid_2018_2023!G6 -> 14.01 | H3: =EPF_Nacional_2018_2023!G6 -> 16.35 | I3: =G3-H3 -> -2.34 | J3: =(EPF_Madrid_2018_2023!G4/EPF_Madrid_2018_2023!B4-1)*100 -> 26.779937 | K3: =(EPF_Nacional_2018_2023!G4/EPF_Nacional_2018_2023!B4-1)*100 -> 26.286366
A4: Bebidas alcohólicas y tabaco | B4: =EPF_Madrid_2018_2023!G7 -> 457.73 | C4: =EPF_Nacional_2018_2023!G7 -> 473.61 | D4: =B4/C4 -> 0.9664703 | E4: =EPF_Madrid_2018_2023!G8 -> 179.49 | F4: =EPF_Nacional_2018_2023!G8 -> 190.51 | G4: =EPF_Madrid_2018_2023!G9 -> 1.23 | H4: =EPF_Nacional_2018_2023!G9 -> 1.45 | I4: =G4-H4 -> -0.22 | J4: =(EPF_Madrid_2018_2023!G7/EPF_Madrid_2018_2023!B7-1)*100 -> -7.2425882 | K4: =(EPF_Nacional_2018_2023!G7/EPF_Nacional_2018_2023!B7-1)*100 -> -8.7245606
A5: Vestido y calzado | B5: =EPF_Madrid_2018_2023!G10 -> 1323.8 | C5: =EPF_Nacional_2018_2023!G10 -> 1319.38 | D5: =B5/C5 -> 1.0033501 | E5: =EPF_Madrid_2018_2023!G11 -> 519.1 | F5: =EPF_Nacional_2018_2023!G11 -> 530.72 | G5: =EPF_Madrid_2018_2023!G12 -> 3.54 | H5: =EPF_Nacional_2018_2023!G12 -> 4.05 | I5: =G5-H5 -> -0.51 | J5: =(EPF_Madrid_2018_2023!G10/EPF_Madrid_2018_2023!B10-1)*100 -> -11.031957 | K5: =(EPF_Nacional_2018_2023!G10/EPF_Nacional_2018_2023!B10-1)*100 -> -9.8235949
A6: Vivienda agua electricidad gas y otros combustibles | B6: =EPF_Madrid_2018_2023!G13 -> 13076.74 | C6: =EPF_Nacional_2018_2023!G13 -> 10367.26 | D6: =B6/C6 -> 1.2613497 | E6: =EPF_Madrid_2018_2023!G14 -> 5127.77 | F6: =EPF_Nacional_2018_2023!G14 -> 4170.25 | G6: =EPF_Madrid_2018_2023!G15 -> 35 | H6: =EPF_Nacional_2018_2023!G15 -> 31.79 | I6: =G6-H6 -> 3.21 | J6: =(EPF_Madrid_2018_2023!G13/EPF_Madrid_2018_2023!B13-1)*100 -> 11.48287 | K6: =(EPF_Nacional_2018_2023!G13/EPF_Nacional_2018_2023!B13-1)*100 -> 12.92389
A7: Muebles y artículos del hogar | B7: =EPF_Madrid_2018_2023!G16 -> 1484.26 | C7: =EPF_Nacional_2018_2023!G16 -> 1349.33 | D7: =B7/C7 -> 1.0999978 | E7: =EPF_Madrid_2018_2023!G17 -> 582.02 | F7: =EPF_Nacional_2018_2023!G17 -> 542.77 | G7: =EPF_Madrid_2018_2023!G18 -> 3.97 | H7: =EPF_Nacional_2018_2023!G18 -> 4.14 | I7: =G7-H7 -> -0.17 | J7: =(EPF_Madrid_2018_2023!G16/EPF_Madrid_2018_2023!B16-1)*100 -> -6.504485 | K7: =(EPF_Nacional_2018_2023!G16/EPF_Nacional_2018_2023!B16-1)*100 -> -1.6458806
A8: Sanidad | B8: =EPF_Madrid_2018_2023!G19 -> 1301.18 | C8: =EPF_Nacional_2018_2023!G19 -> 1242.68 | D8: =B8/C8 -> 1.0470757 | E8: =EPF_Madrid_2018_2023!G20 -> 510.23 | F8: =EPF_Nacional_2018_2023!G20 -> 499.87 | G8: =EPF_Madrid_2018_2023!G21 -> 3.48 | H8: =EPF_Nacional_2018_2023!G21 -> 3.81 | I8: =G8-H8 -> -0.33 | J8: =(EPF_Madrid_2018_2023!G19/EPF_Madrid_2018_2023!B19-1)*100 -> 32.970211 | K8: =(EPF_Nacional_2018_2023!G19/EPF_Nacional_2018_2023!B19-1)*100 -> 23.071743
A9: Transporte | B9: =EPF_Madrid_2018_2023!G22 -> 4146.29 | C9: =EPF_Nacional_2018_2023!G22 -> 3777.71 | D9: =B9/C9 -> 1.097567 | E9: =EPF_Madrid_2018_2023!G23 -> 1625.88 | F9: =EPF_Nacional_2018_2023!G23 -> 1519.59 | G9: =EPF_Madrid_2018_2023!G24 -> 11.1 | H9: =EPF_Nacional_2018_2023!G24 -> 11.58 | I9: =G9-H9 -> -0.48 | J9: =(EPF_Madrid_2018_2023!G22/EPF_Madrid_2018_2023!B22-1)*100 -> -2.2728344 | K9: =(EPF_Nacional_2018_2023!G22/EPF_Nacional_2018_2023!B22-1)*100 -> -0.32979703
A10: Comunicaciones | B10: =EPF_Madrid_2018_2023!G25 -> 1008.64 | C10: =EPF_Nacional_2018_2023!G25 -> 896.08 | D10: =B10/C10 -> 1.1256138 | E10: =EPF_Madrid_2018_2023!G26 -> 395.52 | F10: =EPF_Nacional_2018_2023!G26 -> 360.45 | G10: =EPF_Madrid_2018_2023!G27 -> 2.7 | H10: =EPF_Nacional_2018_2023!G27 -> 2.75 | I10: =G10-H10 -> -0.05 | J10: =(EPF_Madrid_2018_2023!G25/EPF_Madrid_2018_2023!B25-1)*100 -> -4.2645482 | K10: =(EPF_Nacional_2018_2023!G25/EPF_Nacional_2018_2023!B25-1)*100 -> -7.0466074
A11: Ocio y cultura | B11: =EPF_Madrid_2018_2023!G28 -> 1884.54 | C11: =EPF_Nacional_2018_2023!G28 -> 1651.06 | D11: =B11/C11 -> 1.1414122 | E11: =EPF_Madrid_2018_2023!G29 -> 738.98 | F11: =EPF_Nacional_2018_2023!G29 -> 664.14 | G11: =EPF_Madrid_2018_2023!G30 -> 5.04 | H11: =EPF_Nacional_2018_2023!G30 -> 5.06 | I11: =G11-H11 -> -0.02 | J11: =(EPF_Madrid_2018_2023!G28/EPF_Madrid_2018_2023!B28-1)*100 -> -4.9311655 | K11: =(EPF_Nacional_2018_2023!G28/EPF_Nacional_2018_2023!B28-1)*100 -> 0.48078093
A12: Enseñanza | B12: =EPF_Madrid_2018_2023!G31 -> 889.38 | C12: =EPF_Nacional_2018_2023!G31 -> 485.8 | D12: =B12/C12 -> 1.8307534 | E12: =EPF_Madrid_2018_2023!G32 -> 348.75 | F12: =EPF_Nacional_2018_2023!G32 -> 195.42 | G12: =EPF_Madrid_2018_2023!G33 -> 2.38 | H12: =EPF_Nacional_2018_2023!G33 -> 1.49 | I12: =G12-H12 -> 0.89 | J12: =(EPF_Madrid_2018_2023!G31/EPF_Madrid_2018_2023!B31-1)*100 -> 14.798704 | K12: =(EPF_Nacional_2018_2023!G31/EPF_Nacional_2018_2023!B31-1)*100 -> 5.4573872
A13: Restaurantes y hoteles | B13: =EPF_Madrid_2018_2023!G34 -> 3907.52 | C13: =EPF_Nacional_2018_2023!G34 -> 3310.67 | D13: =B13/C13 -> 1.1802807 | E13: =EPF_Madrid_2018_2023!G35 -> 1532.25 | F13: =EPF_Nacional_2018_2023!G35 -> 1331.72 | G13: =EPF_Madrid_2018_2023!G36 -> 10.46 | H13: =EPF_Nacional_2018_2023!G36 -> 10.15 | I13: =G13-H13 -> 0.31 | J13: =(EPF_Madrid_2018_2023!G34/EPF_Madrid_2018_2023!B34-1)*100 -> 3.401447 | K13: =(EPF_Nacional_2018_2023!G34/EPF_Nacional_2018_2023!B34-1)*100 -> 12.319003
A14: Otros bienes y servicios | B14: =EPF_Madrid_2018_2023!G37 -> 2645.18 | C14: =EPF_Nacional_2018_2023!G37 -> 2409.58 | D14: =B14/C14 -> 1.0977764 | E14: =EPF_Madrid_2018_2023!G38 -> 1037.25 | F14: =EPF_Nacional_2018_2023!G38 -> 969.26 | G14: =EPF_Madrid_2018_2023!G39 -> 7.08 | H14: =EPF_Nacional_2018_2023!G39 -> 7.39 | I14: =G14-H14 -> -0.31 | J14: =(EPF_Madrid_2018_2023!G37/EPF_Madrid_2018_2023!B37-1)*100 -> 3.5635982 | K14: =(EPF_Nacional_2018_2023!G37/EPF_Nacional_2018_2023!B37-1)*100 -> 4.8564391
A16: Gasto medio anual por hogar y por persona, 2023 (EPF). Pesos: distribución porcentual del gasto total; la fila TOTAL suma los pesos de control (≈100). La variación 2018–2023 es nominal (sin descontar inflación).

Sheet Cesta_Necesidades_Aprox
A1: Indicador APROXIMADO de coste de las necesidades básicas — Comunidad de Madrid
A2: No existe una "cesta básica" oficial única en España. Se toma como proxy cinco grupos de gasto esenciales, ponderados con el peso del gasto de los hogares de Madrid en 2023 (EPF). Elaboración propia, no dato oficial.
A4: grupo esencial | B4: peso EPF Madrid 2023 (%) | C4: IPC Madrid sep-2025 (% anual) | D4: IPC Madrid sep-2026 (% anual) | E4: gasto hogar Madrid 2023 (€) | F4: gasto hogar España 2023 (€) | G4: peso EPF España 2023 (%) | H4: IPC Madrid sep-2026 − general (pp)
A5: Alimentos y bebidas no alcohólicas | B5: =EPF_Comparativa_2023!G3 -> 14.01 | C5: =IPC_Madrid_Grupos!C3 -> 2.7 | D5: =IPC_Madrid_Grupos!O3 -> 3.2 | E5: =EPF_Comparativa_2023!B3 -> 5235.2 | F5: =EPF_Comparativa_2023!C3 -> 5333.49 | G5: =EPF_Comparativa_2023!H3 -> 16.35 | H5: =D5-D$11 -> -2.1
A6: Vivienda, agua, electricidad, gas y otros combustibles | B6: =EPF_Comparativa_2023!G6 -> 35 | C6: =IPC_Madrid_Grupos!C6 -> 7.8 | D6: =IPC_Madrid_Grupos!O6 -> 5.9 | E6: =EPF_Comparativa_2023!B6 -> 13076.74 | F6: =EPF_Comparativa_2023!C6 -> 10367.26 | G6: =EPF_Comparativa_2023!H6 -> 31.79 | H6: =D6-D$11 -> 0.6
A7: Sanidad | B7: =EPF_Comparativa_2023!G8 -> 3.48 | C7: =IPC_Madrid_Grupos!C8 -> 2.3 | D7: =IPC_Madrid_Grupos!O8 -> 2.6 | E7: =EPF_Comparativa_2023!B8 -> 1301.18 | F7: =EPF_Comparativa_2023!C8 -> 1242.68 | G7: =EPF_Comparativa_2023!H8 -> 3.81 | H7: =D7-D$11 -> -2.7
A8: Transporte | B8: =EPF_Comparativa_2023!G9 -> 11.1 | C8: =IPC_Madrid_Grupos!C9 -> 3.7 | D8: =IPC_Madrid_Grupos!O9 -> 11.5 | E8: =EPF_Comparativa_2023!B9 -> 4146.29 | F8: =EPF_Comparativa_2023!C9 -> 3777.71 | G8: =EPF_Comparativa_2023!H9 -> 11.58 | H8: =D8-D$11 -> 6.2
A9: Enseñanza | B9: =EPF_Comparativa_2023!G12 -> 2.38 | C9: =IPC_Madrid_Grupos!C12 -> 2.8 | D9: =IPC_Madrid_Grupos!O12 -> 2.1 | E9: =EPF_Comparativa_2023!B12 -> 889.38 | F9: =EPF_Comparativa_2023!C12 -> 485.8 | G9: =EPF_Comparativa_2023!H12 -> 1.49 | H9: =D9-D$11 -> -3.2
A10: Suma / media ponderada | B10: =SUM(B5:B9) -> 65.97 | C10: =SUMPRODUCT($B5:$B9,C5:C9)/SUM($B5:$B9) -> 5.5565409 | D10: =SUMPRODUCT($B5:$B9,D5:D9)/SUM($B5:$B9) -> 5.9576777 | E10: =SUM(E5:E9) -> 24648.79 | F10: =SUM(F5:F9) -> 21206.94 | G10: =SUM(G5:G9) -> 65.02
A11: IPC general Madrid (referencia) | C11: =IPC_Madrid_Grupos!C2 -> 3.5 | D11: =IPC_Madrid_Grupos!O2 -> 5.3
A12: Diferencia necesidades básicas − general (pp) | C12: =C10-C11 -> 2.0565409 | D12: =D10-D11 -> 0.65767773
A13: Peso de las 5 necesidades en el gasto total del hogar (Madrid, %) | B13: =E10/EPF_Comparativa_2023!B2*100 -> 65.975589
A14: Peso de las 5 necesidades en el gasto total del hogar (España, %) | B14: =F10/EPF_Comparativa_2023!C2*100 -> 65.018736
A16: Método: media de las tasas de variación anual del IPC de Madrid de los cinco grupos, ponderada por el peso de cada grupo en el gasto medio de los hogares de Madrid (EPF 2023). Es una aproximación: usa tasas anuales en vez de índices encadenados y los pesos del IPC oficial son distintos de los de la EPF. El grupo de vivienda de la EPF incluye también otros gastos de suministros; conviene verificar en la metodología del INE si incluye el alquiler imputado.

Sheet Salario_vs_IPC
A1: anio | B1: salario medio España € | C1: salario mediano España € | D1: salario medio Madrid € | E1: salario mediano Madrid € | F1: IPC España dic/dic % | G1: IPC Madrid dic/dic % | H1: IPC España acumulado (2008=100) | I1: IPC Madrid acumulado (2008=100) | J1: media España nominal (2008=100) | K1: mediana España nominal (2008=100) | L1: media Madrid nominal (2008=100) | M1: mediana Madrid nominal (2008=100) | N1: media España REAL (2008=100) | O1: mediana España REAL (2008=100) | P1: media Madrid REAL (2008=100) | Q1: mediana Madrid REAL (2008=100)
A2: 2008 | B2: 21883.42 | C2: 18244.4 | D2: 25269.61 | E2: 20269.59 | F2: =IPC_General_Anual!B8 -> 1.4 | G2: =IPC_General_Anual!C8 -> 1.6 | H2: 100 | I2: 100 | J2: =B2/B$2*100 -> 100 | K2: =C2/C$2*100 -> 100 | L2: =D2/D$2*100 -> 100 | M2: =E2/E$2*100 -> 100 | N2: =J2/H2*100 -> 100 | O2: =K2/H2*100 -> 100 | P2: =L2/I2*100 -> 100 | Q2: =M2/I2*100 -> 100
A3: 2009 | B3: 22511.47 | C3: 18803.28 | D3: 25860.65 | E3: 20712.42 | F3: =IPC_General_Anual!B9 -> 0.8 | G3: =IPC_General_Anual!C9 -> 0.9 | H3: =H2*(1+F3/100) -> 100.8 | I3: =I2*(1+G3/100) -> 100.9 | J3: =B3/B$2*100 -> 102.86998 | K3: =C3/C$2*100 -> 103.0633 | L3: =D3/D$2*100 -> 102.33894 | M3: =E3/E$2*100 -> 102.1847 | N3: =J3/H3*100 -> 102.05355 | O3: =K3/H3*100 -> 102.24533 | P3: =L3/I3*100 -> 101.4261 | Q3: =M3/I3*100 -> 101.27324
A4: 2010 | B4: 22790.2 | C4: 19017.09 | D4: 25988.95 | E4: 21319.25 | F4: =IPC_General_Anual!B10 -> 3 | G4: =IPC_General_Anual!C10 -> 3 | H4: =H3*(1+F4/100) -> 103.824 | I4: =I3*(1+G4/100) -> 103.927 | J4: =B4/B$2*100 -> 104.14369 | K4: =C4/C$2*100 -> 104.23522 | L4: =D4/D$2*100 -> 102.84666 | M4: =E4/E$2*100 -> 105.1785 | N4: =J4/H4*100 -> 100.30791 | O4: =K4/H4*100 -> 100.39607 | P4: =L4/I4*100 -> 98.960482 | Q4: =M4/I4*100 -> 101.20421
A5: 2011 | B5: 22899.35 | C5: 19303.51 | D5: 25845.2 | E5: 21045.69 | F5: =IPC_General_Anual!B11 -> 2.4 | G5: =IPC_General_Anual!C11 -> 2.5 | H5: =H4*(1+F5/100) -> 106.31578 | I5: =I4*(1+G5/100) -> 106.52518 | J5: =B5/B$2*100 -> 104.64246 | K5: =C5/C$2*100 -> 105.80512 | L5: =D5/D$2*100 -> 102.2778 | M5: =E5/E$2*100 -> 103.82889 | N5: =J5/H5*100 -> 98.426093 | O5: =K5/H5*100 -> 99.519683 | P5: =L5/I5*100 -> 96.012793 | Q5: =M5/I5*100 -> 97.468874
A6: 2012 | B6: 22726.44 | C6: 19040.98 | D6: 26044.39 | E6: 21418.48 | F6: =IPC_General_Anual!B12 -> 2.9 | G6: =IPC_General_Anual!C12 -> 2.5 | H6: =H5*(1+F6/100) -> 109.39893 | I6: =I5*(1+G6/100) -> 109.1883 | J6: =B6/B$2*100 -> 103.85232 | K6: =C6/C$2*100 -> 104.36616 | L6: =D6/D$2*100 -> 103.06605 | M6: =E6/E$2*100 -> 105.66805 | N6: =J6/H6*100 -> 94.929923 | O6: =K6/H6*100 -> 95.399615 | P6: =L6/I6*100 -> 94.392943 | Q6: =M6/I6*100 -> 96.775976
A7: 2013 | B7: 22697.86 | C7: 19029.66 | D7: 26215.36 | E7: 21273.89 | F7: =IPC_General_Anual!B13 -> 0.3 | G7: =IPC_General_Anual!C13 -> 0.2 | H7: =H6*(1+F7/100) -> 109.72713 | I7: =I6*(1+G7/100) -> 109.40668 | J7: =B7/B$2*100 -> 103.72172 | K7: =C7/C$2*100 -> 104.30412 | L7: =D7/D$2*100 -> 103.74264 | M7: =E7/E$2*100 -> 104.95471 | N7: =J7/H7*100 -> 94.526961 | O7: =K7/H7*100 -> 95.057726 | P7: =L7/I7*100 -> 94.822946 | Q7: =M7/I7*100 -> 95.930808
A8: 2014 | B8: 22858.17 | C8: 19263.78 | D8: 26570.35 | E8: 21579.38 | F8: =IPC_General_Anual!B14 -> -1 | G8: =IPC_General_Anual!C14 -> -1.1 | H8: =H7*(1+F8/100) -> 108.62986 | I8: =I7*(1+G8/100) -> 108.20321 | J8: =B8/B$2*100 -> 104.45429 | K8: =C8/C$2*100 -> 105.58736 | L8: =D8/D$2*100 -> 105.14745 | M8: =E8/E$2*100 -> 106.46185 | N8: =J8/H8*100 -> 96.156146 | O8: =K8/H8*100 -> 97.199204 | P8: =L8/I8*100 -> 97.175907 | Q8: =M8/I8*100 -> 98.390658
A9: 2015 | B9: 23106.3 | C9: 19466.49 | D9: 26448.04 | E9: 21307.78 | F9: =IPC_General_Anual!B15 -> 0 | G9: =IPC_General_Anual!C15 -> 0 | H9: =H8*(1+F9/100) -> 108.62986 | I9: =I8*(1+G9/100) -> 108.20321 | J9: =B9/B$2*100 -> 105.58816 | K9: =C9/C$2*100 -> 106.69844 | L9: =D9/D$2*100 -> 104.66343 | M9: =E9/E$2*100 -> 105.12191 | N9: =J9/H9*100 -> 97.19994 | O9: =K9/H9*100 -> 98.222017 | P9: =L9/I9*100 -> 96.728581 | Q9: =M9/I9*100 -> 97.152304
A10: 2016 | B10: 23156.34 | C10: 19432.62 | D10: 26330.14 | E10: 21165 | F10: =IPC_General_Anual!B16 -> 1.6 | G10: =IPC_General_Anual!C16 -> 1.4 | H10: =H9*(1+F10/100) -> 110.36794 | I10: =I9*(1+G10/100) -> 109.71805 | J10: =B10/B$2*100 -> 105.81682 | K10: =C10/C$2*100 -> 106.51279 | L10: =D10/D$2*100 -> 104.19686 | M10: =E10/E$2*100 -> 104.4175 | N10: =J10/H10*100 -> 95.876418 | O10: =K10/H10*100 -> 96.507007 | P10: =L10/I10*100 -> 94.967835 | Q10: =M10/I10*100 -> 95.168937
A11: 2017 | B11: 23646.5 | C11: 19830.12 | D11: 27089.12 | E11: 21608.08 | F11: =IPC_General_Anual!B17 -> 1.1 | G11: =IPC_General_Anual!C17 -> 1.2 | H11: =H10*(1+F11/100) -> 111.58198 | I11: =I10*(1+G11/100) -> 111.03467 | J11: =B11/B$2*100 -> 108.05669 | K11: =C11/C$2*100 -> 108.69154 | L11: =D11/D$2*100 -> 107.20039 | M11: =E11/E$2*100 -> 106.60344 | N11: =J11/H11*100 -> 96.840627 | O11: =K11/H11*100 -> 97.409582 | P11: =L11/I11*100 -> 96.546771 | Q11: =M11/I11*100 -> 96.009147
A12: 2018 | B12: 24009.12 | C12: 20078.44 | D12: 27010.93 | E12: 21477.88 | F12: =IPC_General_Anual!B18 -> 1.2 | G12: =IPC_General_Anual!C18 -> 1.4 | H12: =H11*(1+F12/100) -> 112.92097 | I12: =I11*(1+G12/100) -> 112.58915 | J12: =B12/B$2*100 -> 109.71375 | K12: =C12/C$2*100 -> 110.05262 | L12: =D12/D$2*100 -> 106.89097 | M12: =E12/E$2*100 -> 105.9611 | N12: =J12/H12*100 -> 97.159765 | O12: =K12/H12*100 -> 97.459862 | P12: =L12/I12*100 -> 94.938954 | Q12: =M12/I12*100 -> 94.113059
A13: 2019 | B13: 24395.98 | C13: 20351.02 | D13: 27817.76 | E13: 22262.74 | F13: =IPC_General_Anual!B19 -> 0.8 | G13: =IPC_General_Anual!C19 -> 0.9 | H13: =H12*(1+F13/100) -> 113.82434 | I13: =I12*(1+G13/100) -> 113.60246 | J13: =B13/B$2*100 -> 111.48157 | K13: =C13/C$2*100 -> 111.54667 | L13: =D13/D$2*100 -> 110.08385 | M13: =E13/E$2*100 -> 109.8332 | N13: =J13/H13*100 -> 97.94177 | O13: =K13/H13*100 -> 97.998961 | P13: =L13/I13*100 -> 96.902703 | Q13: =M13/I13*100 -> 96.682067
A14: 2020 | B14: 25165.51 | C14: 20920.12 | D14: 28829.06 | E14: 23231.04 | F14: =IPC_General_Anual!B20 -> -0.5 | G14: =IPC_General_Anual!C20 -> -0.8 | H14: =H13*(1+F14/100) -> 113.25521 | I14: =I13*(1+G14/100) -> 112.69364 | J14: =B14/B$2*100 -> 114.99807 | K14: =C14/C$2*100 -> 114.66598 | L14: =D14/D$2*100 -> 114.08589 | M14: =E14/E$2*100 -> 114.61031 | N14: =J14/H14*100 -> 101.53887 | O14: =K14/H14*100 -> 101.24565 | P14: =L14/I14*100 -> 101.23543 | Q14: =M14/I14*100 -> 101.70078
... A18: 2024 | B18: 29540.26 | C18: 24497.17 | D18: 34410.01 | E18: 28037.75 | F18: =IPC_General_Anual!B24 -> 2.8 | G18: =IPC_General_Anual!C24 -> 2.9 | H18: =H17*(1+F18/100) -> 135.12465 | I18: =I17*(1+G18/100) -> 132.67382 | J18: =B18/B$2*100 -> 134.98923 | K18: =C18/C$2*100 -> 134.27227 | L18: =D18/D$2*100 -> 136.17151 | M18: =E18/E$2*100 -> 138.32421 | N18: =J18/H18*100 -> 99.899781 | O18: =K18/H18*100 -> 99.36919 | P18: =L18/I18*100 -> 102.63631 | Q18: =M18/I18*100 -> 104.25886
A20: Los salarios (azul) proceden de la EES (INE, tabla 28191). El IPC es dic/dic mientras que el salario es anual (media del año), por lo que el cálculo es una aproximación del poder adquisitivo; la columna REAL divide el índice nominal entre el índice de precios acumulado (2008=100).

Sheet ECV_Renta_Pobreza
A1: territorio | B1: serie (renta neta media, €) | C1: 2023 | D1: 2024 | E1: 2025
A2: Total Nacional | B2: Renta neta media por persona | C2: 14082 | D2: 14807 | E2: 15620
A3: Total Nacional | B3: Renta neta media por unidad de consumo | C3: 20676 | D3: 21759 | E3: 22943
A4: Total Nacional | B4: Renta neta media por persona (con alquiler imputado) | C4: 16180 | D4: 16917 | E4: 17914
A5: Total Nacional | B5: Renta neta media por unidad de consumo (con alquiler imputado) | C5: 23574 | D5: 24666 | E5: 26102
A6: Madrid | B6: Renta neta media por persona | C6: 16817 | D6: 17275 | E6: 18169
A7: Madrid | B7: Renta neta media por unidad de consumo | C7: 24991 | D7: 25712 | E7: 27136
A8: Madrid | B8: Renta neta media por persona (con alquiler imputado) | C8: 19041 | D8: 19459 | E8: 20566
A9: Madrid | B9: Renta neta media por unidad de consumo (con alquiler imputado) | C9: 28077 | D9: 28740 | E9: 30471
A11: Madrid / España
B12: Renta neta media por persona | C12: =C6/C2 -> 1.1942196 | D12: =D6/D2 -> 1.1666779 | E12: =E6/E2 -> 1.1631882
B13: Renta neta media por unidad de consumo | C13: =C7/C3 -> 1.2086961 | D13: =D7/D3 -> 1.181672 | E13: =E7/E3 -> 1.1827573
B14: Renta neta media por persona (con alquiler imputado) | C14: =C8/C4 -> 1.1768232 | D14: =D8/D4 -> 1.150263 | E14: =E8/E4 -> 1.1480406
B15: Renta neta media por unidad de consumo (con alquiler imputado) | C15: =C9/C5 -> 1.1910155 | D15: =D9/D5 -> 1.1651666 | E15: =E9/E5 -> 1.1673818
A18: territorio | B18: indicador | C18: unidad | D18: 2020 | E18: 2021 | F18: 2022 | G18: 2023 | H18: 2024 | I18: 2025
A19: Madrid | B19: AROPE (riesgo de pobreza o exclusión social) | C19: % | D19: 21.2 | E19: 21.6 | F19: 20.3 | G19: 19.4 | H19: 20.9 | I19: 19.4
A20: Madrid | B20: En riesgo de pobreza (renta año anterior a la entrevista) | C20: % | D20: 15.4 | E20: 15.2 | F20: 14.8 | G20: 12.9 | H20: 14.3 | I20: 12.7
A21: Madrid | B21: Carencia material y social severa | C21: % | D21: 8.7 | E21: 7.4 | F21: 6.5 | G21: 8.9 | H21: 8.5 | I21: 8.4
A22: Madrid | B22: Baja intensidad en el trabajo (0-64 años) | C22: % | D22: 5.9 | E22: 7.6 | F22: 5.2 | G22: 5.2 | H22: 4.9 | I22: 3.5
A23: Total Nacional | B23: AROPE (riesgo de pobreza o exclusión social) | C23: % | D23: 27 | E23: 27.8 | F23: 26 | G23: 26.5 | H23: 25.8 | I23: 25.7
A24: Total Nacional | B24: En riesgo de pobreza (renta año anterior a la entrevista) | C24: % | D24: 21 | E24: 21.7 | F24: 20.4 | G24: 20.2 | H24: 19.7 | I24: 19.5
A25: Total Nacional | B25: Carencia material y social severa | C25: % | D25: 8.5 | E25: 8.3 | F25: 7.7 | G25: 9 | H25: 8.3 | I25: 8.1
A26: Total Nacional | B26: Baja intensidad en el trabajo (0-64 años) | C26: % | D26: 10 | E26: 11.6 | F26: 8.7 | G26: 8.4 | H26: 8 | I26: 8
A28: Diferencia Madrid − España (pp)
B29: AROPE (riesgo de pobreza o exclusión social) | D29: =D19-D23 -> -5.8 | E29: =E19-E23 -> -6.2 | F29: =F19-F23 -> -5.7 | G29: =G19-G23 -> -7.1 | H29: =H19-H23 -> -4.9 | I29: =I19-I23 -> -6.3
B30: En riesgo de pobreza (renta año anterior a la entrevista) | D30: =D20-D24 -> -5.6 | E30: =E20-E24 -> -6.5 | F30: =F20-F24 -> -5.6 | G30: =G20-G24 -> -7.3 | H30: =H20-H24 -> -5.4 | I30: =I20-I24 -> -6.8
B31: Carencia material y social severa | D31: =D21-D25 -> 0.2 | E31: =E21-E25 -> -0.9 | F31: =F21-F25 -> -1.2 | G31: =G21-G25 -> -0.1 | H31: =H21-H25 -> 0.2 | I31: =I21-I25 -> 0.3
B32: Baja intensidad en el trabajo (0-64 años) | D32: =D22-D26 -> -4.1 | E32: =E22-E26 -> -4 | F32: =F22-F26 -> -3.5 | G32: =G22-G26 -> -3.2 | H32: =H22-H26 -> -3.1 | I32: =I22-I26 -> -4.5
A35: Encuesta de Condiciones de Vida (INE). Renta neta media (tabla 49145; base 2013) y AROPE (tabla 76847, objetivo Europa 2030). Los años son los de la encuesta; las rentas se refieren al año anterior. Fila "con alquiler imputado" incluye el valor del alquiler de la vivienda en propiedad.

Sheet FUENTES
A1: Tema | B1: Organismo | C1: Tabla / identificador | D1: URL (API o página) | E1: Cobertura | F1: Fecha de consulta | G1: Observaciones
A2: IPC general España | B2: INE | C2: Serie IPC290750 (tabla 76134) | D2: https://servicios.ine.es/wstempus/js/ES/DATOS_SERIE/IPC290750?date=20020101:20261001 | E2: 2002–2026-09 | F2: 2026-10-21 | G2: Variación anual.
A3: IPC general Madrid | B3: INE | C3: Serie IPC294331 (tabla 76140) | D3: https://servicios.ine.es/wstempus/js/ES/DATOS_SERIE/IPC294331?date=20020101:20261001 | E3: 2002–2026-09 | F3: 2026-10-21 | G3: Variación anual.
A4: IPC Madrid por grupos | B4: INE | C4: Tabla 76136; series IPC294335…IPC294383 | D4: https://servicios.ine.es/wstempus/js/ES/DATOS_TABLA/76136?nult=14&tv=70:9009&tv=3:74&tip=A | E4: ago-2025 a sep-2026 | F4: 2026-10-21 | G4: Seis grupos se descargaron serie a serie porque el servicio truncaba la tabla (IPC294363, 367, 371, 375, 379, 383).
A5: IPC armonizado | B5: Eurostat | C5: prc_hicp_aind | D5: https://ec.europa.eu/eurostat/api/dissemination/statistics/1.0/data/prc_hicp_aind?geo=ES&unit=RCH_A_AVG&sinceTimePeriod=2005&coicop=CP00&format=JSON | E5: España; 2005–2025 | F5: 2026-10-21 | G5: Una petición por grupo. Dataset discontinuado (ver prc_hicp_ainr).
A6: Gasto de los hogares | B6: INE | C6: EPF tabla 14505 | D6: https://servicios.ine.es/wstempus/js/ES/DATOS_TABLA/14505?nult=6&tv=70:9009&tip=A | E6: Madrid y Total Nacional; 2018–2023 | F6: 2026-10-21 | G6: Variante nacional con tv=349:16473.
A7: Renta media | B7: INE | C7: ECV tabla 49145 | D7: https://servicios.ine.es/wstempus/js/ES/DATOS_TABLA/49145?nult=3&tip=A | E7: 2023–2025 | F7: 2026-10-21
A8: AROPE | B8: INE | C8: ECV tabla 76847 | D8: https://servicios.ine.es/wstempus/js/ES/DATOS_TABLA/76847?nult=6&tv=70:9009&tip=A | E8: 2020–2025 | F8: 2026-10-21 | G8: Variante nacional con tv=349:16473.
A9: Salarios (para Salario_vs_IPC) | B9: INE | C9: EES tabla 28191 | D9: https://servicios.ine.es/wstempus/js/ES/DATOS_TABLA/28191?nult=17&tip=A | E9: 2008–2024 | F9: 2026-10-21 | G9: Copiado a la hoja como dato fijo; ver 02_Salarios.xlsx.
